<?xml version="1.0" encoding="UTF-8"?>
<data>
  <viestit>
    <viesti lähettäjä="Ville">moi</viesti>
    <viesti lähettäjä="Ville">moi</viesti>
    <viesti lähettäjä="Ville">moi</viesti>
    <viesti lähettäjä="Ville">moi</viesti>
    <viesti lähettäjä="Ville">moi</viesti>
    <viesti lähettäjä="Ville">moi</viesti>
    <viesti lähettäjä="ville">321</viesti>
    <viesti lähettäjä="ville">321</viesti>
    <viesti lähettäjä="21">1233</viesti>
    <viesti lähettäjä="21">1233</viesti>
    <viesti lähettäjä="21">1233</viesti>
    <viesti lähettäjä="villeee">toimiiko</viesti>
  </viestit>
</data>
